censusdis/__init__.py
censusdis/cli/__init__.py
censusdis/cli/cli.py
censusdis/cli/yamlspec.py
censusdis/counties/alabama.py
censusdis/counties/alaska.py
censusdis/counties/arizona.py
censusdis/counties/arkansas.py
censusdis/counties/california.py
censusdis/counties/colorado.py
censusdis/counties/connecticut.py
censusdis/counties/delaware.py
censusdis/counties/district_of_columbia.py
censusdis/counties/florida.py
censusdis/counties/georgia.py
censusdis/counties/hawaii.py
censusdis/counties/idaho.py
censusdis/counties/illinois.py
censusdis/counties/indiana.py
censusdis/counties/iowa.py
censusdis/counties/kansas.py
censusdis/counties/kentucky.py
censusdis/counties/louisiana.py
censusdis/counties/maine.py
censusdis/counties/maryland.py
censusdis/counties/massachusetts.py
censusdis/counties/michigan.py
censusdis/counties/minnesota.py
censusdis/counties/mississippi.py
censusdis/counties/missouri.py
censusdis/counties/montana.py
censusdis/counties/nebraska.py
censusdis/counties/nevada.py
censusdis/counties/new_hampshire.py
censusdis/counties/new_jersey.py
censusdis/counties/new_mexico.py
censusdis/counties/new_york.py
censusdis/counties/north_carolina.py
censusdis/counties/north_dakota.py
censusdis/counties/ohio.py
censusdis/counties/oklahoma.py
censusdis/counties/oregon.py
censusdis/counties/pennsylvania.py
censusdis/counties/puerto_rico.py
censusdis/counties/rhode_island.py
censusdis/counties/south_carolina.py
censusdis/counties/south_dakota.py
censusdis/counties/tennessee.py
censusdis/counties/texas.py
censusdis/counties/utah.py
censusdis/counties/vermont.py
censusdis/counties/virginia.py
censusdis/counties/washington.py
censusdis/counties/west_virginia.py
censusdis/counties/wisconsin.py
censusdis/counties/wyoming.py
censusdis/csa.py
censusdis/data.py
censusdis/datasets.py
censusdis/division.py
censusdis/geography.py
censusdis/impl/__init__.py
censusdis/impl/exceptions.py
censusdis/impl/fetch.py
censusdis/impl/geometry.py
censusdis/impl/us_census_shapefiles.py
censusdis-1.4.2.dist-info/LICENSE.md
censusdis-1.4.2.dist-info/METADATA
censusdis-1.4.2.dist-info/WHEEL
censusdis-1.4.2.dist-info/entry_points.txt
censusdis-1.4.2.dist-info/RECORD
