Metadata-Version: 2.1
Name: censusdis
Version: 1.4.2
Summary: US Census utilities for a variety of data loading, analysis, and mapping purposes.
Home-page: https://github.com/vengroff/censusdis
License: HL3-CL-ECO-EXTR-FFD-LAW-MIL-SV
Keywords: census,demographics
Author: Darren Vengroff
Requires-Python: >=3.10,<4.0
Classifier: Development Status :: 4 - Beta
Classifier: Intended Audience :: Science/Research
Classifier: License :: Other/Proprietary License
Classifier: Operating System :: MacOS :: MacOS X
Classifier: Operating System :: Microsoft :: Windows
Classifier: Operating System :: POSIX :: Linux
Classifier: Programming Language :: Python :: 3
Classifier: Programming Language :: Python :: 3.10
Classifier: Programming Language :: Python :: 3.11
Classifier: Programming Language :: Python :: 3.12
Classifier: Programming Language :: Python :: 3.13
Provides-Extra: docs
Provides-Extra: explore
Provides-Extra: jupyterlab
Requires-Dist: Fiona (>=1.10.0,<2.0.0)
Requires-Dist: PyYAML (>=6.0,<7.0)
Requires-Dist: Rtree (>=1.0.0,<2.0.0)
Requires-Dist: Sphinx (>=6.1.3,<7.0.0) ; extra == "docs"
Requires-Dist: adjustText (>=0.8,<0.9)
Requires-Dist: certifi (==2025.01.31)
Requires-Dist: contextily (>=1.3.0,<2.0.0)
Requires-Dist: divintseg (>=0.7.0,<0.8.0)
Requires-Dist: folium (>=0.17.0,<0.18.0) ; extra == "explore"
Requires-Dist: geopandas (==1.0.1)
Requires-Dist: geopy (>=2.2.0,<3.0.0)
Requires-Dist: haversine (>=2.8.0,<3.0.0)
Requires-Dist: ipyleaflet (>=0.19.0,<0.20.0) ; extra == "explore"
Requires-Dist: ipywidgets (>=8.1.3,<9.0.0) ; extra == "jupyterlab"
Requires-Dist: jinja2 (>=3.1.4)
Requires-Dist: jupyterlab (>=4.2.3,<5.0.0) ; extra == "jupyterlab"
Requires-Dist: logargparser (>=0.1.1,<0.2.0)
Requires-Dist: mapclassify (>=2.7.0,<3.0.0) ; extra == "explore"
Requires-Dist: matplotlib (>=3.9.1,<4.0.0)
Requires-Dist: nbsphinx (>=0.9.3,<0.10.0)
Requires-Dist: numpy (>=2.0.0,<3.0.0)
Requires-Dist: pyarrow (>=18.0.0,<19.0.0)
Requires-Dist: pyogrio (>=0.10.0,<0.11.0)
Requires-Dist: rasterio (>=1.3.10,<2.0.0)
Requires-Dist: requests (>=2.32.0,<3.0.0)
Requires-Dist: sphinx-copybutton (>=0.5.1,<0.6.0) ; extra == "docs"
Requires-Dist: sphinx-rtd-theme (==2.0.0) ; extra == "docs"
Requires-Dist: sphinxcontrib-napoleon (==0.7) ; extra == "docs"
Requires-Dist: toml (>=0.10.2,<0.11.0) ; extra == "docs"
Requires-Dist: usingversion (>=0.1.1,<0.2.0)
Project-URL: Repository, https://github.com/vengroff/censusdis
